lib_mpgs_api_client/__init__.py
lib_mpgs_api_client/client.py
lib_mpgs_api_client/const.py
libmpgsapiclient-0.0.1.dist-info/LICENSE
libmpgsapiclient-0.0.1.dist-info/METADATA
libmpgsapiclient-0.0.1.dist-info/WHEEL
libmpgsapiclient-0.0.1.dist-info/top_level.txt
libmpgsapiclient-0.0.1.dist-info/RECORD
